angostura_connection.json
explanation.html
service_account.json
c4v/__init__.py
c4v/c4v_cli.py
c4v/classifier/__init__.py
c4v/classifier/base_model.py
c4v/classifier/classifier.py
c4v/classifier/classifier_experiment.py
c4v/classifier/data_gathering/client_dataset_reformat.py
c4v/classifier/data_gathering/create_confirmation_dataset.py
c4v/classifier/data_gathering/create_training_csv.py
c4v/classifier/data_gathering/primicia_irrelevant_news_scraping.py
c4v/classifier/data_gathering/primicia_irrelevant_news_wrangle.py
c4v/classifier/experiment.py
c4v/classifier/language_model/language_model.py
c4v/classifier/language_model/language_model_experiment.py
c4v/cloud/gcloud_storage_manager.py
c4v/cloud/utils.py
c4v/config.py
c4v/dashboard/app.py
c4v/dashboard/main.py
c4v/data/angostura_loader.py
c4v/data/baseline_models.py
c4v/data/data_loader.py
c4v/data/data_sampler.py
c4v/data/tweet_loader.py
c4v/microscope/__init__.py
c4v/microscope/manager.py
c4v/microscope/metadata.py
c4v/microscope/utils.py
c4v/scraper/__init__.py
c4v/scraper/crawler/__init__.py
c4v/scraper/crawler/crawlers/__init__.py
c4v/scraper/crawler/crawlers/base_crawler.py
c4v/scraper/crawler/crawlers/el_pitazo_crawler.py
c4v/scraper/crawler/crawlers/primicia_crawler.py
c4v/scraper/persistency_manager/__init__.py
c4v/scraper/persistency_manager/base_persistency_manager.py
c4v/scraper/persistency_manager/big_query_persistency_manager.py
c4v/scraper/persistency_manager/example_dict_manager.py
c4v/scraper/persistency_manager/sqlite_storage_manager.py
c4v/scraper/scraped_data_classes/base_scraped_data.py
c4v/scraper/scraped_data_classes/elpitazo_scraped_data.py
c4v/scraper/scraped_data_classes/primicia_scraped_data.py
c4v/scraper/scraped_data_classes/scraped_data.py
c4v/scraper/scraper.py
c4v/scraper/scrapers/__init__.py
c4v/scraper/scrapers/base_scraper.py
c4v/scraper/scrapers/base_scrapy_scraper.py
c4v/scraper/scrapers/el_pitazo_scraper.py
c4v/scraper/scrapers/primicia_scraper.py
c4v_py-0.1.0.dev202210127.dist-info/entry_points.txt
c4v_py-0.1.0.dev202210127.dist-info/WHEEL
c4v_py-0.1.0.dev202210127.dist-info/METADATA
c4v_py-0.1.0.dev202210127.dist-info/RECORD
