Metadata-Version: 2.1
Name: c4v-py
Version: 0.1.0.dev202210127
Summary: Code for Venezuela python library.
Home-page: https://www.codeforvenezuela.org/
License: Apache-2.0
Keywords: NLP,NLU,Machine Learning,ipython,jupyter,widgets,brat,annotation
Author: Edilmo Palencia
Author-email: edilmo@gmail.com
Requires-Python: >=3.6.2,<4.0
Classifier: License :: OSI Approved :: Apache Software License
Classifier: Programming Language :: Python :: 3
Classifier: Programming Language :: Python :: 3.7
Classifier: Programming Language :: Python :: 3.8
Classifier: Programming Language :: Python :: 3.9
Provides-Extra: all
Provides-Extra: classification
Provides-Extra: dashboard
Provides-Extra: gcloud
Provides-Extra: jupyter
Provides-Extra: tensorflow
Requires-Dist: Flask (>=2.0.2,<3.0.0); extra == "gcloud" or extra == "all"
Requires-Dist: Scrapy (>=2.5.0,<3.0.0)
Requires-Dist: beautifulsoup4 (>=4.9.3,<5.0.0)
Requires-Dist: click (==7.1.2)
Requires-Dist: dataclasses (>=0.8.0,<0.9.0); python_version >= "3.6.1" and python_version < "3.7"
Requires-Dist: datasets (>=1.10.2,<2.0.0); extra == "classification" or extra == "all"
Requires-Dist: dynaconf (>=3.1.4,<4.0.0)
Requires-Dist: google-cloud-bigquery (==1.26.1); extra == "gcloud" or extra == "all"
Requires-Dist: google-cloud-logging (>=2.7.0,<3.0.0); extra == "gcloud" or extra == "all"
Requires-Dist: google-cloud-storage (>=1.43.0,<2.0.0); extra == "gcloud" or extra == "all"
Requires-Dist: importlib-metadata (>=4.6.1,<5.0.0)
Requires-Dist: importlib-resources (>=5.2.2,<6.0.0)
Requires-Dist: ipykernel (==5.5.5); extra == "jupyter" or extra == "all"
Requires-Dist: ipython (==7.16.1); extra == "jupyter" or extra == "all"
Requires-Dist: nbconvert (==5.6.1)
Requires-Dist: nltk (>=3.5,<4.0)
Requires-Dist: pandas (==1.1.1); extra == "classification" or extra == "all"
Requires-Dist: pip (>=21.0.0,<22.0.0)
Requires-Dist: pytz (>=2021.3,<2022.0)
Requires-Dist: scikit-learn (==0.23.1); extra == "classification" or extra == "all"
Requires-Dist: scikit-multilearn (==0.2.0); extra == "classification" or extra == "all"
Requires-Dist: scipy (==1.5.4)
Requires-Dist: streamlit (>=1.2.0,<2.0.0); extra == "dashboard" or extra == "all"
Requires-Dist: tabulate (>=0.8.9,<0.9.0)
Requires-Dist: tensorflow (>=2.5.2,<3.0.0); extra == "tensorflow" or extra == "all"
Requires-Dist: tensorflow-probability (==0.10.0); extra == "tensorflow" or extra == "all"
Requires-Dist: tensorflow_hub[make_image_classifier] (==0.8.0); extra == "tensorflow" or extra == "all"
Requires-Dist: torch (>=1.9.0,<1.10.0); extra == "classification" or extra == "all"
Requires-Dist: traitlets (==4.3.3)
Requires-Dist: transformers (>=4.9.0,<5.0.0); extra == "classification" or extra == "all"
Requires-Dist: transformers-interpret (>=0.5.2,<0.6.0); extra == "classification" or extra == "all"
Requires-Dist: zipp (>=3.5.0,<4.0.0)
Project-URL: Repository, https://github.com/dieko95/c4v-py
